<?xml version="1.0" encoding="utf-8" ?>
<blz:ENTITY ALIAS="GROUP" TEMPALIAS="GROUP 157"  EXPIRY_DAYS="60" TYPE="GROUP" DESCRIPTION="From column map of GROUP to GROUP starting column map id 2031" PRIMARY_FEED="IBM_MANAGED_SERVERS" xmlns:blz="http://www.blazent.com/xmlbeans/connectorconfig" >
	<ATTRIBUTE NAME="DATA_PARTITION_CODE" FEED="IBM_MANAGED_SERVERS" HEADER="DATA_PARTITION_CODE"  />
	<ATTRIBUTE NAME="TENANT_CODE" FEED="IBM_MANAGED_SERVERS" HEADER="TENANT_CODE"  />
	<ATTRIBUTE NAME="SOURCE_CODE" FEED="IBM_MANAGED_SERVERS" HEADER="SOURCE_CODE"  />
	<ATTRIBUTE NAME="TENANT_DATA_PARTITION_ID" FEED="IBM_MANAGED_SERVERS" HEADER="TENANT_DATA_PARTITION_ID"  />
	<ATTRIBUTE NAME="GROUP_NAME" FEED="IBM_MANAGED_SERVERS" HEADER="GROUP_NAME" ISPRIMARY="true"  />
	<ATTRIBUTE NAME="GROUP_NAME_O" FEED="IBM_MANAGED_SERVERS" HEADER="GROUP_NAME"  />
	<ATTRIBUTE NAME="IF_SOURCE_ID" FEED="IBM_MANAGED_SERVERS" HEADER="IF_SOURCE_ID"  />
	<ATTRIBUTE NAME="DATE_FORMAT_MASK" FEED="IBM_MANAGED_SERVERS" HEADER="DATE_FORMAT_MASK"  />
	<ATTRIBUTE NAME="TIME_ZONE" FEED="IBM_MANAGED_SERVERS" HEADER="TIME_ZONE"  />
</blz:ENTITY>

