<?xml version="1.0" encoding="UTF-8"?>
<blz:ENTITY ALIAS="ONX_PO" TEMPALIAS="ONX_PO"  EXPIRY_DAYS="60" TYPE="PURCHASE_ORDER" DESCRIPTION="" PRIMARY_FEED="ONX_PO_LINE_ITEM" xmlns:blz="http://www.blazent.com/xmlbeans/connectorconfig" >
	<ATTRIBUTE NAME="TENANT_CODE" FEED="ONX_PO_LINE_ITEM" HEADER="TENANT_CODE"  />
	<ATTRIBUTE NAME="DATA_PARTITION_CODE" FEED="ONX_PO_LINE_ITEM" HEADER="DATA_PARTITION_CODE"  />
	<ATTRIBUTE NAME="TENANT_DATA_PARTITION_ID" FEED="ONX_PO_LINE_ITEM" HEADER="TENANT_DATA_PARTITION_ID"  />
	<ATTRIBUTE NAME="IF_SOURCE_ID" FEED="ONX_PO_LINE_ITEM" HEADER="IF_SOURCE_ID"  />
	<ATTRIBUTE NAME="SOURCE_CODE" FEED="ONX_PO_LINE_ITEM" HEADER="SOURCE_CODE"  />
	<ATTRIBUTE NAME="DATE_FORMAT_MASK" FEED="ONX_PO_LINE_ITEM" HEADER="DATE_FORMAT_MASK"  />
	<ATTRIBUTE NAME="TIME_ZONE" FEED="ONX_PO_LINE_ITEM" HEADER="TIME_ZONE"  />
	<ATTRIBUTE NAME="VENDOR" FEED="ONX_PO_LINE_ITEM" HEADER="VENDOR" />
	<ATTRIBUTE NAME="PURCHASE_SYSTEM_PO_NUMBER" FEED="ONX_PO_LINE_ITEM" HEADER="PURCHASING_SYSTEM_PO_NUMBER" PROCESS="UPPER_TRIM" />
	<ATTRIBUTE NAME="PURCHASE_SYSTEM_PO_NUMBER_M" FEED="ONX_PO_LINE_ITEM" HEADER="PURCHASING_SYSTEM_PO_NUMBER" ISPRIMARY="true" PROCESS="UPPER_TRIM" />
	<ATTRIBUTE NAME="PURCHASE_SYSTEM_PO_NUMBER_O" FEED="ONX_PO_LINE_ITEM" HEADER="PURCHASING_SYSTEM_PO_NUMBER" PROCESS="UPPER_TRIM"  />
	<ATTRIBUTE NAME="PO_DATE" FEED="ONX_PO_LINE_ITEM" HEADER="PO_DATE" PROCESS="CONVERT_TO_STANDARD_TIME" />
	<ATTRIBUTE NAME="PO_DATE_C" FEED="ONX_PO_LINE_ITEM" HEADER="PO_DATE"  />
	<ATTRIBUTE NAME="PO_DATE_O" FEED="ONX_PO_LINE_ITEM" HEADER="PO_DATE_O"  />
	<ATTRIBUTE NAME="PO_COST_CENTER" FEED="ONX_PO_LINE_ITEM" HEADER="PO_COST_CENTER"	/>
	<ATTRIBUTE NAME="PO_COST_CENTER_O" FEED="ONX_PO_LINE_ITEM" HEADER="PO_COST_CENTER"	/>
	<ATTRIBUTE NAME="PO_CONTACT" FEED="ONX_PO_LINE_ITEM" HEADER="PO_CONTACT"	/>
	<ATTRIBUTE NAME="PO_CONTACT_O" FEED="ONX_PO_LINE_ITEM" HEADER="PO_CONTACT"	/>
	<ATTRIBUTE NAME="PO_TOTAL_COST" FEED="ONX_PO_LINE_ITEM" HEADER="PO_TOTAL_COST"	/>
	<ATTRIBUTE NAME="PO_TOTAL_COST_O" FEED="ONX_PO_LINE_ITEM" HEADER="PO_TOTAL_COST_O"	/>
</blz:ENTITY>